Metadata-Version: 2.4
Name: hatch-xclam
Version: 0.7.1
Summary: Package manager for the Cracking Shells ecosystem
Author: Cracking Shells Team
Project-URL: Homepage, https://github.com/CrackingShells/Hatch
Project-URL: Bug Tracker, https://github.com/CrackingShells/Hatch/issues
Classifier: Programming Language :: Python :: 3.12
Classifier: License :: OSI Approved :: GNU Affero General Public License v3
Classifier: Operating System :: OS Independent
Requires-Python: >=3.12
License-File: LICENSE
Requires-Dist: jsonschema>=4.0.0
Requires-Dist: requests>=2.25.0
Requires-Dist: packaging>=20.0
Requires-Dist: docker>=7.1.0
Requires-Dist: pydantic>=2.0.0
Requires-Dist: hatch-validator>=0.8.0
Requires-Dist: tomli-w>=1.0.0
Provides-Extra: docs
Requires-Dist: mkdocs>=1.4.0; extra == "docs"
Requires-Dist: mkdocstrings[python]>=0.20.0; extra == "docs"
Provides-Extra: dev
Requires-Dist: wobble>=0.2.0; extra == "dev"
Dynamic: license-file
